gpxprofpy/__init__.py
gpxprofpy/main.py
gpxprofpy/params.py
gpxprofpy/points.py
gpxprofpy/profile.py
gpxprofpy/segments.py
gpxprofpy/utils.py
gpxprofpy-0.1.0.dist-info/METADATA
gpxprofpy-0.1.0.dist-info/WHEEL
gpxprofpy-0.1.0.dist-info/licenses/LICENSE
gpxprofpy-0.1.0.dist-info/RECORD
